Metadata-Version: 1.0
Name: peppercompiler
Version: 0.1.3
Summary: PepperCompiler in a pythonic form
Home-page: UNKNOWN
Author: Constantine Evans et al (this version)
Author-email: cge@dna.caltech.edu
License: UNKNOWN
Platform: UNKNOWN
